pypkgs/__init__.py
pypkgs/cli.py
pypkgs/pypkgs.py
pypkgs-0.1.1.dist-info/entry_points.txt
pypkgs-0.1.1.dist-info/LICENSE
pypkgs-0.1.1.dist-info/WHEEL
pypkgs-0.1.1.dist-info/METADATA
pypkgs-0.1.1.dist-info/RECORD
