Metadata-Version: 2.1
Name: pypkgs
Version: 0.1.1
Summary: Python package that eases the pain of concatenating Pandas categoricals!
Home-page: https://github.com/TomasBeuzen/pypkgs
License: MIT
Author: Tomas Beuzen
Author-email: tomas.beuzen@gmail.com
Requires-Python: >=3.7,<4.0
Classifier: License :: OSI Approved :: MIT License
Classifier: Programming Language :: Python :: 3
Classifier: Programming Language :: Python :: 3.7
Classifier: Programming Language :: Python :: 3.8
Requires-Dist: pandas (>=1.0.5,<2.0.0)
Project-URL: Documentation, https://pybeach.readthedocs.io
Project-URL: Repository, https://github.com/TomasBeuzen/pypkgs
